Cielab-1.0.0.dist-info/LICENSE
Cielab-1.0.0.dist-info/METADATA
Cielab-1.0.0.dist-info/WHEEL
Cielab-1.0.0.dist-info/top_level.txt
Cielab-1.0.0.dist-info/RECORD
Cielab.libs/libgomp-01467509.so.1.0.0
Cielab/__init__.pxd
Cielab/Cielab.pyx
Cielab/Cielab.cpython-38-i386-linux-gnu.so
Cielab/config.py
Cielab/Cielab.cpp
Cielab/Cielab.pxd
Cielab/__init__.py
Cielab/Demo/demo.py
Cielab/Demo/__init__.py
Cielab/Include/Cielab_c.c
Cielab/tests/profiler.py
Cielab/tests/test_cielab.py
Cielab/tests/__init__.py
Cielab/Assets/adobe_surface.png
Cielab/Assets/background32.png
Cielab/Assets/white_surf.png
Cielab/Assets/demo.png
Cielab/Assets/cielab_surface.png
Cielab/Assets/background2.png
Cielab-1.0.0.data/data/lib/site-packages/Cielab/LICENSE
Cielab-1.0.0.data/data/lib/site-packages/Cielab/__init__.pxd
Cielab-1.0.0.data/data/lib/site-packages/Cielab/pyproject.toml
Cielab-1.0.0.data/data/lib/site-packages/Cielab/Cielab.pyx
Cielab-1.0.0.data/data/lib/site-packages/Cielab/config.py
Cielab-1.0.0.data/data/lib/site-packages/Cielab/Cielab.pxd
Cielab-1.0.0.data/data/lib/site-packages/Cielab/README.md
Cielab-1.0.0.data/data/lib/site-packages/Cielab/requirements.txt
Cielab-1.0.0.data/data/lib/site-packages/Cielab/MANIFEST.in
Cielab-1.0.0.data/data/lib/site-packages/Cielab/__init__.py
Cielab-1.0.0.data/data/lib/site-packages/Cielab/Demo/demo.py
Cielab-1.0.0.data/data/lib/site-packages/Cielab/Demo/__init__.py
Cielab-1.0.0.data/data/lib/site-packages/Cielab/Include/Cielab_c.c
Cielab-1.0.0.data/data/lib/site-packages/Cielab/tests/profiler.py
Cielab-1.0.0.data/data/lib/site-packages/Cielab/tests/test_cielab.py
Cielab-1.0.0.data/data/lib/site-packages/Cielab/tests/__init__.py
Cielab-1.0.0.data/data/lib/site-packages/Cielab/Assets/adobe_surface.png
Cielab-1.0.0.data/data/lib/site-packages/Cielab/Assets/background32.png
Cielab-1.0.0.data/data/lib/site-packages/Cielab/Assets/white_surf.png
Cielab-1.0.0.data/data/lib/site-packages/Cielab/Assets/demo.png
Cielab-1.0.0.data/data/lib/site-packages/Cielab/Assets/cielab_surface.png
Cielab-1.0.0.data/data/lib/site-packages/Cielab/Assets/background2.png
