Metadata-Version: 2.1
Name: Cielab
Version: 1.0.0
Summary: Cielab color space
Home-page: https://github.com/yoyoberenguer/Cielab
Author: Yoann Berenguer
Author-email: yoyoberenguer@hotmail.com
License: GNU General Public License v3.0
Project-URL: Bug Reports, https://github.com/yoyoberenguer/Cielab/issues
Project-URL: Source, https://github.com/yoyoberenguer/Cielab
Platform: Windows
Classifier: Development Status :: 4 - Beta
Classifier: Intended Audience :: Developers
Classifier: Topic :: Software Development :: Build Tools
Classifier: Operating System :: Microsoft :: Windows
Classifier: Operating System :: POSIX :: Linux
Classifier: Programming Language :: Cython
Classifier: License :: OSI Approved :: GNU General Public License v3 (GPLv3)
Classifier: Programming Language :: Python :: 3.6
Classifier: Programming Language :: Python :: 3.7
Classifier: Programming Language :: Python :: 3.8
Classifier: Programming Language :: Python :: 3.9
Classifier: Programming Language :: Python :: 3.10
Classifier: Programming Language :: Python :: 3.11
Classifier: Topic :: Scientific/Engineering :: Image Processing
Classifier: Topic :: Software Development :: Libraries :: Python Modules
Classifier: Topic :: Software Development :: Libraries
Requires-Python: >=3.6
Requires-Dist: setuptools (>=49.2.1)
Requires-Dist: Cython (>=0.28)
Requires-Dist: numpy (>=1.18)
Requires-Dist: pygame (>=2.0)
